[{"Name": "Person", "Confidence": 99.70663452148438, "Instances": [{"BoundingBox": {"Width": 0.3260820806026459, "Height": 0.8867949843406677, "Left": 0.04651545733213425, "Top": 0.10114146023988724}, "Confidence": 99.70663452148438}, {"BoundingBox": {"Width": 0.3301942050457001, "Height": 0.622948169708252, "Left": 0.5926885008811951, "Top": 0.2760806381702423}, "Confidence": 99.58531188964844}], "Parents": []}, {"Name": "Human", "Confidence": 99.70663452148438, "Instances": [], "Parents": []}, {"Name": "Sitting", "Confidence": 99.21638488769531, "Instances": [], "Parents": [{"Name": "Person"}]}, {"Name": "Clothing", "Confidence": 98.92727661132812, "Instances": [], "Parents": []}, {"Name": "Apparel", "Confidence": 98.92727661132812, "Instances": [], "Parents": []}, {"Name": "Microphone", "Confidence": 95.25743865966797, "Instances": [{"BoundingBox": {"Width": 0.04865439981222153, "Height": 0.24781659245491028, "Left": 0.1801270693540573, "Top": 0.2983572781085968}, "Confidence": 95.25743865966797}], "Parents": [{"Name": "Electrical Device"}]}, {"Name": "Electrical Device", "Confidence": 95.25743865966797, "Instances": [], "Parents": []}, {"Name": "Shoe", "Confidence": 76.35733795166016, "Instances": [], "Parents": [{"Name": "Footwear"}, {"Name": "Clothing"}]}, {"Name": "Footwear", "Confidence": 76.35733795166016, "Instances": [], "Parents": [{"Name": "Clothing"}]}]