[{"Name": "Flyer", "Confidence": 95.09236907958984, "Instances": [{"BoundingBox": {"Width": 0.9682642221450806, "Height": 0.9203410744667053, "Left": 0.013852889649569988, "Top": 0.06517218053340912}, "Confidence": 95.09236907958984}], "Parents": [{"Name": "Poster"}, {"Name": "Paper"}, {"Name": "Advertisement"}]}, {"Name": "Paper", "Confidence": 95.09236907958984, "Instances": [], "Parents": []}, {"Name": "Brochure", "Confidence": 95.09236907958984, "Instances": [], "Parents": [{"Name": "Poster"}, {"Name": "Paper"}, {"Name": "Advertisement"}]}, {"Name": "Advertisement", "Confidence": 95.09236907958984, "Instances": [], "Parents": []}, {"Name": "Poster", "Confidence": 95.09236907958984, "Instances": [], "Parents": [{"Name": "Advertisement"}]}]