[{"Name": "Audience", "Confidence": 98.26596069335938, "Instances": [], "Parents": [{"Name": "Crowd"}, {"Name": "Person"}]}, {"Name": "Crowd", "Confidence": 98.26596069335938, "Instances": [], "Parents": [{"Name": "Person"}]}, {"Name": "Person", "Confidence": 98.26596069335938, "Instances": [{"BoundingBox": {"Width": 0.21043401956558228, "Height": 0.7714833617210388, "Left": 0.2178509384393692, "Top": 0.20880787074565887}, "Confidence": 93.07308959960938}, {"BoundingBox": {"Width": 0.21565832197666168, "Height": 0.6815666556358337, "Left": 0.5201478004455566, "Top": 0.3053094744682312}, "Confidence": 92.069091796875}], "Parents": []}, {"Name": "Human", "Confidence": 98.26596069335938, "Instances": [], "Parents": []}, {"Name": "Suit", "Confidence": 96.62654113769531, "Instances": [{"BoundingBox": {"Width": 0.21085533499717712, "Height": 0.641007125377655, "Left": 0.212081640958786, "Top": 0.3451930582523346}, "Confidence": 96.62654113769531}, {"BoundingBox": {"Width": 0.1986885964870453, "Height": 0.5670996308326721, "Left": 0.5308337807655334, "Top": 0.4212115705013275}, "Confidence": 93.3231430053711}], "Parents": [{"Name": "Overcoat"}, {"Name": "Coat"}, {"Name": "Clothing"}]}, {"Name": "Coat", "Confidence": 96.62654113769531, "Instances": [], "Parents": [{"Name": "Clothing"}]}, {"Name": "Overcoat", "Confidence": 96.62654113769531, "Instances": [], "Parents": [{"Name": "Coat"}, {"Name": "Clothing"}]}, {"Name": "Clothing", "Confidence": 96.62654113769531, "Instances": [], "Parents": []}, {"Name": "Apparel", "Confidence": 96.62654113769531, "Instances": [], "Parents": []}, {"Name": "Speech", "Confidence": 95.8757553100586, "Instances": [], "Parents": [{"Name": "Audience"}, {"Name": "Crowd"}, {"Name": "Person"}]}, {"Name": "Lecture", "Confidence": 78.22611999511719, "Instances": [], "Parents": [{"Name": "Speech"}, {"Name": "Audience"}, {"Name": "Crowd"}, {"Name": "Person"}]}]