[{"Name": "Poster", "Confidence": 99.70326232910156, "Instances": [], "Parents": [{"Name": "Advertisement"}]}, {"Name": "Advertisement", "Confidence": 99.70326232910156, "Instances": [], "Parents": []}, {"Name": "Flyer", "Confidence": 99.68810272216797, "Instances": [{"BoundingBox": {"Width": 0.9852834343910217, "Height": 0.980667233467102, "Left": 0.008938712067902088, "Top": 0.013322349637746811}, "Confidence": 67.6031265258789}], "Parents": [{"Name": "Poster"}, {"Name": "Paper"}, {"Name": "Advertisement"}]}, {"Name": "Brochure", "Confidence": 99.68810272216797, "Instances": [], "Parents": [{"Name": "Poster"}, {"Name": "Paper"}, {"Name": "Advertisement"}]}, {"Name": "Paper", "Confidence": 99.68810272216797, "Instances": [], "Parents": []}]