[{"Name": "Person", "Confidence": 95.739990234375, "Instances": [{"BoundingBox": {"Width": 0.3887106478214264, "Height": 0.5389682650566101, "Left": 0.33541950583457947, "Top": 0.43710705637931824}, "Confidence": 95.4495620727539}, {"BoundingBox": {"Width": 0.2246977984905243, "Height": 0.36603647470474243, "Left": 0.26525694131851196, "Top": 0.5979323387145996}, "Confidence": 52.55177688598633}], "Parents": []}, {"Name": "Human", "Confidence": 95.739990234375, "Instances": [], "Parents": []}, {"Name": "Text", "Confidence": 81.82987213134766, "Instances": [], "Parents": []}, {"Name": "Advertisement", "Confidence": 79.59996032714844, "Instances": [], "Parents": []}, {"Name": "Poster", "Confidence": 78.030029296875, "Instances": [], "Parents": [{"Name": "Advertisement"}]}, {"Name": "Sitting", "Confidence": 76.07327270507812, "Instances": [], "Parents": [{"Name": "Person"}]}]